subdomains/__init__.py
subdomains/middleware.py
subdomains/models.py
subdomains/utils.py
django_subdomains2-4.1.2.dist-info/LICENSE
django_subdomains2-4.1.2.dist-info/METADATA
django_subdomains2-4.1.2.dist-info/WHEEL
django_subdomains2-4.1.2.dist-info/top_level.txt
django_subdomains2-4.1.2.dist-info/RECORD
