Metadata-Version: 2.1
Name: django-subdomains2
Version: 4.1.2
Summary: Subdomain tools for the Django framework, including subdomain-based URL routing.
Author-email: lhy <dev@lhy.kr>
License: Copyright (c) 2022 LeeHanYeong
Project-URL: GitHub, https://github.com/LeeHanYeong/django-subdomains
Classifier: Framework :: Django
Classifier: Framework :: Django :: 3.2
Classifier: Framework :: Django :: 4.0
Classifier: Programming Language :: Python
Requires-Python: >=3.8
License-File: LICENSE
Requires-Dist: django
